opentelemetry/sdk/__init__.pyi
opentelemetry/sdk/environment_variables.py
opentelemetry/sdk/py.typed
opentelemetry/sdk/version.py
opentelemetry/sdk/_configuration/__init__.py
opentelemetry/sdk/_logs/__init__.py
opentelemetry/sdk/_logs/severity.py
opentelemetry/sdk/_logs/export/__init__.py
opentelemetry/sdk/_logs/export/in_memory_log_exporter.py
opentelemetry/sdk/error_handler/__init__.py
opentelemetry/sdk/metrics/__init__.py
opentelemetry/sdk/metrics/_internal/__init__.py
opentelemetry/sdk/metrics/_internal/_view_instrument_match.py
opentelemetry/sdk/metrics/_internal/aggregation.py
opentelemetry/sdk/metrics/_internal/exceptions.py
opentelemetry/sdk/metrics/_internal/instrument.py
opentelemetry/sdk/metrics/_internal/measurement.py
opentelemetry/sdk/metrics/_internal/measurement_consumer.py
opentelemetry/sdk/metrics/_internal/metric_reader_storage.py
opentelemetry/sdk/metrics/_internal/point.py
opentelemetry/sdk/metrics/_internal/sdk_configuration.py
opentelemetry/sdk/metrics/_internal/view.py
opentelemetry/sdk/metrics/_internal/export/__init__.py
opentelemetry/sdk/metrics/export/__init__.py
opentelemetry/sdk/metrics/view/__init__.py
opentelemetry/sdk/resources/__init__.py
opentelemetry/sdk/trace/__init__.py
opentelemetry/sdk/trace/id_generator.py
opentelemetry/sdk/trace/sampling.py
opentelemetry/sdk/trace/export/__init__.py
opentelemetry/sdk/trace/export/in_memory_span_exporter.py
opentelemetry/sdk/util/__init__.py
opentelemetry/sdk/util/__init__.pyi
opentelemetry/sdk/util/instrumentation.py
opentelemetry_sdk-1.12.0.dist-info/LICENSE
opentelemetry_sdk-1.12.0.dist-info/METADATA
opentelemetry_sdk-1.12.0.dist-info/WHEEL
opentelemetry_sdk-1.12.0.dist-info/entry_points.txt
opentelemetry_sdk-1.12.0.dist-info/top_level.txt
opentelemetry_sdk-1.12.0.dist-info/RECORD
